twitter_scraper_selenium/__init__.py
twitter_scraper_selenium/driver_initialization.py
twitter_scraper_selenium/driver_utils.py
twitter_scraper_selenium/element_finder.py
twitter_scraper_selenium/keyword.py
twitter_scraper_selenium/keyword_api.py
twitter_scraper_selenium/profile.py
twitter_scraper_selenium/profile_api.py
twitter_scraper_selenium/profile_details.py
twitter_scraper_selenium/scraping_utilities.py
twitter_scraper_selenium/topic.py
twitter_scraper_selenium/topic_api.py
twitter_scraper_selenium/utils.py
twitter_scraper_selenium-6.2.2.dist-info/LICENSE
twitter_scraper_selenium-6.2.2.dist-info/METADATA
twitter_scraper_selenium-6.2.2.dist-info/WHEEL
twitter_scraper_selenium-6.2.2.dist-info/top_level.txt
twitter_scraper_selenium-6.2.2.dist-info/RECORD
