Metadata-Version: 2.1
Name: twitter_scraper_selenium
Version: 6.2.2
Summary: Python package to scrap twitter's front-end easily with selenium
Home-page: https://github.com/shaikhsajid1111/twitter-scraper-selenium
Author: Sajid Shaikh
Author-email: shaikhsajid3732@gmail.com
License: MIT
Keywords: web-scraping selenium social media twitter keyword twitter-profile twitter-keywords automation json csv twitter-hashtag hashtag
Classifier: Development Status :: 4 - Beta
Classifier: Environment :: Console
Classifier: Intended Audience :: Developers
Classifier: Intended Audience :: Science/Research
Classifier: Natural Language :: English
Classifier: Programming Language :: Python :: 3
Classifier: Programming Language :: Python :: 3.6
Classifier: Programming Language :: Python :: 3.7
Classifier: Programming Language :: Python :: 3.8
Classifier: Programming Language :: Python :: 3.9
Classifier: Programming Language :: Python :: 3.10
Classifier: Programming Language :: Python :: Implementation :: CPython
Classifier: License :: OSI Approved :: MIT License
Classifier: Operating System :: Microsoft :: Windows
Classifier: Operating System :: POSIX :: Linux
Classifier: Operating System :: MacOS
Classifier: Topic :: Software Development :: Libraries :: Python Modules
Classifier: Topic :: Internet :: WWW/HTTP
Requires-Python: >=3.8
License-File: LICENSE
Requires-Dist: python-dateutil ==2.8.2
Requires-Dist: selenium ==4.7.0
Requires-Dist: selenium-wire ==5.1.0
Requires-Dist: webdriver-manager ==4.0.2
Requires-Dist: fake-headers ==1.0.2
Requires-Dist: requests ==2.27.1
Requires-Dist: blinker ==1.7.0
Requires-Dist: setuptools ==74.1.1
